Tensorflow20KuaisuRumenZhinanChuyi/README.md
Tensorflow20KuaisuRumenZhinanChuyi/__init__.py
Tensorflow20KuaisuRumenZhinanChuyi/__main__.py
Tensorflow20KuaisuRumenZhinanChuyi/file.epub
Tensorflow20KuaisuRumenZhinanChuyi/index.html
Tensorflow20KuaisuRumenZhinanChuyi/css/__init__.py
Tensorflow20KuaisuRumenZhinanChuyi/css/annotations.css
Tensorflow20KuaisuRumenZhinanChuyi/css/main.css
Tensorflow20KuaisuRumenZhinanChuyi/css/normalize.css
Tensorflow20KuaisuRumenZhinanChuyi/css/popup.css
Tensorflow20KuaisuRumenZhinanChuyi/font/__init__.py
Tensorflow20KuaisuRumenZhinanChuyi/font/fontello.eot
Tensorflow20KuaisuRumenZhinanChuyi/font/fontello.svg
Tensorflow20KuaisuRumenZhinanChuyi/font/fontello.ttf
Tensorflow20KuaisuRumenZhinanChuyi/font/fontello.woff
Tensorflow20KuaisuRumenZhinanChuyi/img/__init__.py
Tensorflow20KuaisuRumenZhinanChuyi/img/annotator-glyph-sprite.png
Tensorflow20KuaisuRumenZhinanChuyi/img/annotator-icon-sprite.png
Tensorflow20KuaisuRumenZhinanChuyi/img/apple-touch-icon.png
Tensorflow20KuaisuRumenZhinanChuyi/img/cancelfullscreen.png
Tensorflow20KuaisuRumenZhinanChuyi/img/close.png
Tensorflow20KuaisuRumenZhinanChuyi/img/fullscreen.png
Tensorflow20KuaisuRumenZhinanChuyi/img/loader.gif
Tensorflow20KuaisuRumenZhinanChuyi/img/menu-icon.png
Tensorflow20KuaisuRumenZhinanChuyi/img/save.png
Tensorflow20KuaisuRumenZhinanChuyi/img/saved.png
Tensorflow20KuaisuRumenZhinanChuyi/img/settings-s.png
Tensorflow20KuaisuRumenZhinanChuyi/img/settings.png
Tensorflow20KuaisuRumenZhinanChuyi/img/star.png
Tensorflow20KuaisuRumenZhinanChuyi/js/__init__.py
Tensorflow20KuaisuRumenZhinanChuyi/js/epub.js
Tensorflow20KuaisuRumenZhinanChuyi/js/epub.min.js
Tensorflow20KuaisuRumenZhinanChuyi/js/epub.min.map
Tensorflow20KuaisuRumenZhinanChuyi/js/hooks.min.js
Tensorflow20KuaisuRumenZhinanChuyi/js/hooks.min.map
Tensorflow20KuaisuRumenZhinanChuyi/js/reader.js
Tensorflow20KuaisuRumenZhinanChuyi/js/reader.js.map
Tensorflow20KuaisuRumenZhinanChuyi/js/reader.min.js
tensorflow_2_0_kuaisu_rumen_zhinan_chuyi-2024.3.5.0.dist-info/METADATA
tensorflow_2_0_kuaisu_rumen_zhinan_chuyi-2024.3.5.0.dist-info/WHEEL
tensorflow_2_0_kuaisu_rumen_zhinan_chuyi-2024.3.5.0.dist-info/entry_points.txt
tensorflow_2_0_kuaisu_rumen_zhinan_chuyi-2024.3.5.0.dist-info/top_level.txt
tensorflow_2_0_kuaisu_rumen_zhinan_chuyi-2024.3.5.0.dist-info/RECORD
